Coolcalci/__init__.py
Coolcalci/get_operations.py
Coolcalci/main.py
Coolcalci-3.0.8.dist-info/METADATA
Coolcalci-3.0.8.dist-info/WHEEL
Coolcalci-3.0.8.dist-info/top_level.txt
Coolcalci-3.0.8.dist-info/RECORD
