Metadata-Version: 2.1
Name: Coolcalci
Version: 3.0.8
Summary: This will you to do Arithmetic operations very fast.
Home-page: UNKNOWN
Author: Python Rohan
Author-email: rohan9878787@gmail.com
License: UNKNOWN
Keywords: python,calculator,calci,calculate,calculation,Arithmetic
Platform: UNKNOWN
Classifier: Development Status :: 1 - Planning
Classifier: Intended Audience :: Developers
Classifier: Programming Language :: Python :: 3
Classifier: Operating System :: Unix
Classifier: Operating System :: MacOS :: MacOS X
Classifier: Operating System :: Microsoft :: Windows
